seciva/__init__.py
seciva/seciva.py
seciva-0.1.1.dist-info/METADATA
seciva-0.1.1.dist-info/WHEEL
seciva-0.1.1.dist-info/top_level.txt
seciva-0.1.1.dist-info/RECORD
