Metadata-Version: 2.1
Name: seciva
Version: 0.1.1
Summary: Реализация многослойной нейронной сети на python
Home-page: https://github.com/kovalevich/seciva
Author: Евгений Ковалевич
Author-email: evgen.kovalevich@gmail.com
License: UNKNOWN
Platform: UNKNOWN
Classifier: Programming Language :: Python :: 3
Classifier: License :: OSI Approved :: MIT License
Classifier: Operating System :: OS Independent
Requires-Python: >=3.8
